BUG REPORT COMMENTS:
When compiling the following class:

public class Main
{
    public static void main (String [] args)
    {
    	StringBuffer s1 = new StringBuffer ();
        s1.append (new StringBuffer ());
    }

} // end of class

Eclipse 2.1 GA will emit code that uses Java 1.4-only StringBuffer.append
(StringBuffer) method regardless of JDK or .class compliance level settings 
[the following javap dump was obtained when using JDK 1.3 compatibility with 
default compliance settings]:

Compiled from Main.java
public class Main extends java.lang.Object {
    public Main();
    public static void main(java.lang.String[]);
}

Method Main()
   0 aload_0
   1 invokespecial #9 <Method java.lang.Object()>
   4 return

Method void main(java.lang.String[])
   0 new #17 <Class java.lang.StringBuffer>
   3 dup
   4 invokespecial #18 <Method java.lang.StringBuffer()>
   7 astore_1
   8 aload_1
   9 new #17 <Class java.lang.StringBuffer>
  12 dup
  13 invokespecial #18 <Method java.lang.StringBuffer()>
  16 invokevirtual #22 <Method 

